gmailapi_backend/__init__.py
gmailapi_backend/mail.py
gmailapi_backend/bin/__init__.py
gmailapi_backend/bin/gmail_oauth2.py
django_gmailapi_backend-0.3.2.dist-info/LICENSE
django_gmailapi_backend-0.3.2.dist-info/METADATA
django_gmailapi_backend-0.3.2.dist-info/WHEEL
django_gmailapi_backend-0.3.2.dist-info/entry_points.txt
django_gmailapi_backend-0.3.2.dist-info/top_level.txt
django_gmailapi_backend-0.3.2.dist-info/RECORD
