Metadata-Version: 2.1
Name: django-gmailapi-backend
Version: 0.3.2
Summary: Email backend for Django which sends email via the Gmail API
Home-page: https://github.com/dolfim/django-gmailapi-backend
Author: Michele Dolfi
Author-email: michele.dolfi@gmail.com
License: Apache License 2.0
Platform: UNKNOWN
Classifier: Intended Audience :: Developers
Classifier: License :: OSI Approved :: Apache Software License
Classifier: Operating System :: MacOS :: MacOS X
Classifier: Operating System :: Microsoft :: Windows
Classifier: Operating System :: POSIX
Classifier: Programming Language :: Python
Classifier: Programming Language :: Python :: 3
Classifier: Programming Language :: Python :: 3.5
Classifier: Programming Language :: Python :: 3.6
Classifier: Programming Language :: Python :: 3.7
Classifier: Programming Language :: Python :: 3.8
Classifier: Framework :: Django
Classifier: Topic :: Communications :: Email
Classifier: Development Status :: 4 - Beta
License-File: LICENSE
